blstatus/__init__.py
blstatus/battery.py
blstatus/blstatus.py
blstatus/config.py
blstatus/date_time.py
blstatus/disabled.py
blstatus/inhibit.py
blstatus/memory.py
blstatus/network.py
blstatus/power_profile.py
blstatus/volume.py
blstatus-0.4.dist-info/licenses/LICENSE
blstatus-0.4.dist-info/METADATA
blstatus-0.4.dist-info/WHEEL
blstatus-0.4.dist-info/entry_points.txt
blstatus-0.4.dist-info/top_level.txt
blstatus-0.4.dist-info/RECORD
