Metadata-Version: 2.4
Name: blstatus
Version: 0.4
Summary: A status monitor for DWM or other window managers that use WM_NAME
Author-email: Brenton Leighton <12228142+brenton-leighton@users.noreply.github.com>
Maintainer-email: Brenton Leighton <12228142+brenton-leighton@users.noreply.github.com>
License: MIT License
Project-URL: Homepage, https://github.com/brenton-leighton/blstatus
Keywords: dwm
Requires-Python: >=3.9
License-File: LICENSE
Requires-Dist: apscheduler
Requires-Dist: asyncio-glib
Requires-Dist: pulsectl-asyncio
Requires-Dist: pydbus
Requires-Dist: xlib
Dynamic: license-file
